itk/IOMeshSWCPython.py
itk/_IOMeshSWCPython.pyd
itk/__init_iomeshswc__.py
itk/itkSWCMeshIOPython.py
itk/Configuration/IOMeshSWCConfig.py
itk/Configuration/IOMeshSWC_snake_case.py
itk_iomeshswc.libs/msvcp140.dll
itk_iomeshswc-0.2.0.dist-info/DELVEWHEEL
itk_iomeshswc-0.2.0.dist-info/LICENSE
itk_iomeshswc-0.2.0.dist-info/METADATA
itk_iomeshswc-0.2.0.dist-info/WHEEL
itk_iomeshswc-0.2.0.dist-info/top_level.txt
itk_iomeshswc-0.2.0.dist-info/RECORD
