Metadata-Version: 2.1
Name: itk-iomeshswc
Version: 0.2.0
Summary: ITK module for reading meshes from SWC files, a format for representing neuron morphology.
Home-page: https://itk.org/
Download-URL: https://github.com/InsightSoftwareConsortium/ITKIOMeshSWC
Author: Matt McCormick
Author-email: matt.mccormick@kitware.com
License: Apache
Keywords: ITK InsightToolkit
Classifier: License :: OSI Approved :: Apache Software License
Classifier: Programming Language :: Python
Classifier: Programming Language :: C++
Classifier: Development Status :: 4 - Beta
Classifier: Intended Audience :: Developers
Classifier: Intended Audience :: Education
Classifier: Intended Audience :: Healthcare Industry
Classifier: Intended Audience :: Science/Research
Classifier: Topic :: Scientific/Engineering
Classifier: Topic :: Scientific/Engineering :: Medical Science Apps.
Classifier: Topic :: Scientific/Engineering :: Information Analysis
Classifier: Topic :: Software Development :: Libraries
Classifier: Operating System :: Android
Classifier: Operating System :: Microsoft :: Windows
Classifier: Operating System :: POSIX
Classifier: Operating System :: Unix
Classifier: Operating System :: MacOS
License-File: LICENSE
Requires-Dist: itk-io (>=5.3.0)
